banglanum2words/__init__.py
banglanum2words/num_convert.py
banglanum2words-0.0.3.dist-info/LICENSE
banglanum2words-0.0.3.dist-info/METADATA
banglanum2words-0.0.3.dist-info/WHEEL
banglanum2words-0.0.3.dist-info/top_level.txt
banglanum2words-0.0.3.dist-info/RECORD
