Metadata-Version: 2.1
Name: banglanum2words
Version: 0.0.3
Summary: Converts a Bangla numeric string to literal words.
Home-page: https://github.com/dv66/bangla-number-in-words
Author: Syed Mostofa Monsur
Author-email: mostofamonsur9396@gmail.com
License: UNKNOWN
Project-URL: Bug Tracker, https://github.com/dv66/bangla-number-in-words/issues
Platform: UNKNOWN
Classifier: Programming Language :: Python :: 3
Classifier: License :: OSI Approved :: MIT License
Classifier: Operating System :: OS Independent
Requires-Python: >=3.6
License-File: LICENSE
Requires-Dist: num2words (==0.5.10)
